[{"timestamp":1700726758533,"files":[{"filename":"contentScript.js","previous":1261,"size":1269,"diff":8}]},{"timestamp":1700726716832,"files":[{"filename":"contentScript.js","previous":1256,"size":1261,"diff":5}]},{"timestamp":1700726698894,"files":[{"filename":"contentScript.js","previous":1250,"size":1256,"diff":6}]},{"timestamp":1700726185820,"files":[{"filename":"contentScript.js","previous":1229,"size":1250,"diff":21}]},{"timestamp":1700726124987,"files":[{"filename":"contentScript.js","previous":1219,"size":1229,"diff":10}]},{"timestamp":1700725966701,"files":[{"filename":"contentScript.js","previous":1239,"size":1219,"diff":-20}]},{"timestamp":1700725924784,"files":[{"filename":"contentScript.js","previous":1163,"size":1239,"diff":76}]},{"timestamp":1700725880253,"files":[{"filename":"contentScript.js","previous":1175,"size":1163,"diff":-12}]},{"timestamp":1700725763616,"files":[{"filename":"contentScript.js","previous":1171,"size":1175,"diff":4}]},{"timestamp":1700725703825,"files":[{"filename":"contentScript.js","previous":1151,"size":1171,"diff":20}]},{"timestamp":1700725656512,"files":[{"filename":"contentScript.js","previous":1149,"size":1151,"diff":2}]},{"timestamp":1700725627904,"files":[{"filename":"contentScript.js","previous":842,"size":1149,"diff":307}]},{"timestamp":1700725586453,"files":[{"filename":"contentScript.js","previous":836,"size":842,"diff":6}]},{"timestamp":1700725551512,"files":[{"filename":"contentScript.js","previous":829,"size":836,"diff":7}]},{"timestamp":1700725254139,"files":[{"filename":"contentScript.js","previous":1114,"size":829,"diff":-285}]},{"timestamp":1700725144758,"files":[{"filename":"contentScript.js","previous":1117,"size":1114,"diff":-3}]},{"timestamp":1700724855653,"files":[{"filename":"contentScript.js","previous":1130,"size":1117,"diff":-13}]},{"timestamp":1700724832168,"files":[{"filename":"contentScript.js","previous":1117,"size":1130,"diff":13}]},{"timestamp":1700724605104,"files":[{"filename":"contentScript.js","previous":1076,"size":1117,"diff":41}]},{"timestamp":1700724478463,"files":[{"filename":"contentScript.js","previous":1068,"size":1076,"diff":8}]},{"timestamp":1700724285482,"files":[{"filename":"contentScript.js","previous":1042,"size":1068,"diff":26}]},{"timestamp":1700724112038,"files":[{"filename":"contentScript.js","previous":1052,"size":1042,"diff":-10}]},{"timestamp":1700723680234,"files":[{"filename":"contentScript.js","previous":1040,"size":1052,"diff":12}]},{"timestamp":1700723612030,"files":[{"filename":"contentScript.js","previous":1039,"size":1040,"diff":1}]},{"timestamp":1700723318905,"files":[{"filename":"contentScript.js","previous":667,"size":1039,"diff":372}]},{"timestamp":1700714700571,"files":[{"filename":"contentScript.js","previous":668,"size":667,"diff":-1},{"filename":"popup.css","previous":733,"size":0,"diff":-733},{"filename":"popup.js","previous":995,"size":0,"diff":-995}]},{"timestamp":1700714527389,"files":[{"filename":"contentScript.js","previous":643,"size":668,"diff":25},{"filename":"popup.css","previous":733,"size":733,"diff":0},{"filename":"popup.js","previous":995,"size":995,"diff":0}]},{"timestamp":1700714495706,"files":[{"filename":"contentScript.js","previous":935,"size":643,"diff":-292},{"filename":"popup.css","previous":733,"size":733,"diff":0},{"filename":"popup.js","previous":1047,"size":995,"diff":-52}]},{"timestamp":1700713954831,"files":[{"filename":"contentScript.js","previous":937,"size":935,"diff":-2},{"filename":"popup.css","previous":733,"size":733,"diff":0},{"filename":"popup.js","previous":1051,"size":1047,"diff":-4}]},{"timestamp":1590044186843,"files":[{"filename":"contentScript.js","previous":919,"size":937,"diff":18},{"filename":"popup.css","previous":733,"size":733,"diff":0},{"filename":"popup.js","previous":889,"size":1051,"diff":162}]},{"timestamp":1590037636573,"files":[{"filename":"contentScript.js","previous":879,"size":919,"diff":40},{"filename":"popup.css","previous":733,"size":733,"diff":0},{"filename":"popup.js","previous":889,"size":889,"diff":0}]},{"timestamp":1589987869345,"files":[{"filename":"contentScript.js","previous":883,"size":879,"diff":-4},{"filename":"popup.css","previous":692,"size":733,"diff":41},{"filename":"popup.js","previous":893,"size":889,"diff":-4}]},{"timestamp":1589985118225,"files":[{"filename":"contentScript.js","previous":1118,"size":883,"diff":-235},{"filename":"popup.css","previous":678,"size":692,"diff":14},{"filename":"popup.js","previous":1049,"size":893,"diff":-156}]},{"timestamp":1584103523738,"files":[{"filename":"contentScript.js","previous":2143,"size":1118,"diff":-1025},{"filename":"popup.css","previous":678,"size":678,"diff":0},{"filename":"popup.html","previous":533,"size":0,"diff":-533},{"filename":"popup.js","previous":2197,"size":1049,"diff":-1148}]}]
